Workbook

Sheet Dashboard
A2: REAL ESTATE ACQUISITION MODEL
A3: Investment Dashboard
A6: DEAL OVERVIEW
A9: Purchase Price | B9: Initial Equity | C9: LTV | D9: Hold Period (Years)
A10: =Assumptions!B3 -> 12000000 | B10: ='Debt Schedule'!B2-'Debt Schedule'!B4 -> 3600000 | C10: =Assumptions!B22 -> 0.7 | D10: =Assumptions!B25 -> 5
A14: OPERATING PERFORMANCE
A20: Year 1 NOI | B20: Year 5 NOI | C20: NOI Growth | F20: Year 1 | G20: Year 2 | H20: Year 3 | I20: Year 4 | J20: Year 5
A21: =NOI!B4 -> 1176320 | B21: =NOI!F4 -> 1332883.2 | C21: =(B21/A21)-1 -> 0.1330958 | E21: NOI | F21: =NOI!B4 -> 1176320 | G21: =NOI!C4 -> 1213662.4 | H21: =NOI!D4 -> 1252179.1 | I21: =NOI!E4 -> 1291906.8 | J21: =NOI!F4 -> 1332883.2
A33: INVESTMENT RETURNS
A36: IRR | B36: Equity Multiple | C36: NPV
A37: =Returns!B10 -> 0.39835451 | B37: =Returns!B9 -> 4.3931901 | C37: =Returns!B11 -> 7509421.7
C38: At 8% discount rate
A40: Year 1 CoC ----------------> Year 5 CoC
A41: =Returns!B4 -> 0.15268227 | C41: =Returns!B8 -> 0.19617206
A45: SENSITIVITY ANALYSIS
C47: {='Sensitivity Analysis'!A2:F7} -> Exit Cap Rate / Purchase Price | D47: 10000000 | E47: 11000000 | F47: 12000000 | G47: 13000000 | H47: 14000000
C48: 0.055 | D48: 0.56398805 | E48: 0.50819452 | F48: 0.45800774 | G48: 0.41220987 | H48: 0.3698999
C49: 0.06 | D49: 0.53458995 | E49: 0.47805008 | F49: 0.42704507 | G49: 0.38034515 | H49: 0.33703681
C50: 0.065 | D50: 0.50760029 | E50: 0.4502511 | F50: 0.39835451 | G50: 0.35066553 | H50: 0.30625396
C51: 0.07 | D51: 0.48261726 | E51: 0.42439833 | F51: 0.37153717 | G51: 0.32276949 | H51: 0.27714296
C52: 0.075 | D52: 0.45932651 | E52: 0.40017846 | F52: 0.34627845 | G52: 0.2963377 | H52: 0.24937467
A55: KEY ASSUMPTIONS
A58: Rent Growth | B58: Vacancy | C58: Other Income Growth | D58: LTV | E58: Interest Rate | F58: Hold Period (Years) | G58: Exit Cap Rate
A59: =Assumptions!B8 -> 0.03 | B59: =Assumptions!B7 -> 0.05 | C59: =Assumptions!B9 -> 0.02 | D59: =Assumptions!B22 -> 0.7 | E59: =Assumptions!B23 -> 0.0625 | F59: =Assumptions!B25 -> 5 | G59: =Assumptions!B26 -> 0.065

Sheet Assumptions
A2: Property Information
A3: Purchase Price | B3: 12000000
A4: Units | B4: 100
A5: Average Monthly Rent | B5: 1500
A6: Other Monthly Income per Unit | B6: 50
A7: Vacancy Rate | B7: 0.05
A8: Annual Rent Growth | B8: 0.03
A9: Other Income Growth | B9: 0.02
A11: Operating Expenses
A12: Property Taxes | B12: 180000
A13: Insurance | B13: 60000
A14: Repairs and Maintenance | B14: 120000
A15: Property Management (% of Revenue) | B15: 0.04
A16: Utilities | B16: 90000
A17: Other Expenses | B17: 50000
A18: Operating Expense Growth | B18: 0.025
A19: Administrative | B19: 20000
A21: Financing
A22: Loan-to-Value | B22: 0.7
A23: Interest Rate | B23: 0.0625
A24: Loan Term (Years) | B24: 30
A25: Holding Period (Years) | B25: 5
A26: Exit Cap Rate | B26: 0.065
A27: Discount Rate | B27: 0.08
A29: =Returns!B10 -> 0.39835451 | B29: 10000000 | C29: 11000000 | D29: 12000000 | E29: 13000000 | F29: 14000000
A30: 0.055 | B30: 0.56398805 | C30: 0.50819452 | D30: 0.45800774 | E30: 0.41220987 | F30: 0.3698999
A31: 0.06 | B31: 0.53458995 | C31: 0.47805008 | D31: 0.42704507 | E31: 0.38034515 | F31: 0.33703681
A32: 0.065 | B32: 0.50760029 | C32: 0.4502511 | D32: 0.39835451 | E32: 0.35066553 | F32: 0.30625396
A33: 0.07 | B33: 0.48261726 | C33: 0.42439833 | D33: 0.37153717 | E33: 0.32276949 | F33: 0.27714296
A34: 0.075 | B34: 0.45932651 | C34: 0.40017846 | D34: 0.34627845 | E34: 0.2963377 | F34: 0.24937467

Sheet Revenue
B1: Year 1 | C1: Year 2 | D1: Year 3 | E1: Year 4 | F1: Year 5
A2: Gross Rental Income | B2: =Assumptions!B4*Assumptions!B5*12 -> 1800000 | C2: =B2*(1+Assumptions!B8) -> 1854000 | D2: =C2*(1+Assumptions!B8) -> 1909620 | E2: =D2*(1+Assumptions!B8) -> 1966908.6 | F2: =E2*(1+Assumptions!B8) -> 2025915.9
A3: Other Income | B3: =Assumptions!B4*Assumptions!B6*12 -> 60000 | C3: =B3*(1+Assumptions!B9) -> 61200 | D3: =C3*(1+Assumptions!B9) -> 62424 | E3: =D3*(1+Assumptions!B9) -> 63672.48 | F3: =E3*(1+Assumptions!B9) -> 64945.93
A4: Gross Potential Income | B4: =B2+B3 -> 1860000 | C4: =C2+C3 -> 1915200 | D4: =D2+D3 -> 1972044 | E4: =E2+E3 -> 2030581.1 | F4: =F2+F3 -> 2090861.8
A6: Vacancy Loss | B6: =B4*Assumptions!B7 -> 93000 | C6: =C4*Assumptions!B7 -> 95760 | D6: =D4*Assumptions!B7 -> 98602.2 | E6: =E4*Assumptions!B7 -> 101529.05 | F6: =F4*Assumptions!B7 -> 104543.09
A7: Effective Gross Income | B7: =B4-B6 -> 1767000 | C7: =C4-C6 -> 1819440 | D7: =D4-D6 -> 1873441.8 | E7: =E4-E6 -> 1929052 | F7: =F4-F6 -> 1986318.7

Sheet Expenses
A2: Expense | B2: Year 1 | C2: Year 2 | D2: Year 3 | E2: Year 4 | F2: Year 5
A3: Property Taxes | B3: =Assumptions!B12 -> 180000 | C3: =Expenses!B3*(1+Assumptions!B18) -> 184500 | D3: =C3*(1+Assumptions!B18) -> 189112.5 | E3: =D3*(1+Assumptions!B18) -> 193840.31 | F3: =E3*(1+Assumptions!B18) -> 198686.32
A4: Insurance | B4: =Assumptions!B13 -> 60000 | C4: =B4*(1+Assumptions!B18) -> 61500 | D4: =C4*(1+Assumptions!B18) -> 63037.5 | E4: =D4*(1+Assumptions!B18) -> 64613.437 | F4: =E4*(1+Assumptions!B18) -> 66228.773
A5: Repairs & Maintenance | B5: =Assumptions!B14 -> 120000 | C5: =B5*(1+Assumptions!B18) -> 123000 | D5: =C5*(1+Assumptions!B18) -> 126075 | E5: =D5*(1+Assumptions!B18) -> 129226.87 | F5: =E5*(1+Assumptions!B18) -> 132457.55
A6: Property Management | B6: =Revenue!B7*Assumptions!B15 -> 70680 | C6: =Revenue!C7*Assumptions!B15 -> 72777.6 | D6: =Revenue!D7*Assumptions!B15 -> 74937.672 | E6: =Revenue!E7*Assumptions!B15 -> 77162.081 | F6: =Revenue!F7*Assumptions!B15 -> 79452.748
A7: Utilities | B7: =Assumptions!B16 -> 90000 | C7: =B7*(1+Assumptions!B18) -> 92250 | D7: =C7*(1+Assumptions!B18) -> 94556.25 | E7: =D7*(1+Assumptions!B18) -> 96920.156 | F7: =E7*(1+Assumptions!B18) -> 99343.16
A8: Administrative | B8: =Assumptions!B19 -> 20000 | C8: =B8*(1+Assumptions!B18) -> 20500 | D8: =C8*(1+Assumptions!B18) -> 21012.5 | E8: =D8*(1+Assumptions!B18) -> 21537.812 | F8: =E8*(1+Assumptions!B18) -> 22076.258
A9: Other Expenses | B9: =Assumptions!B17 -> 50000 | C9: =B9*(1+Assumptions!B18) -> 51250 | D9: =C9*(1+Assumptions!B18) -> 52531.25 | E9: =D9*(1+Assumptions!B18) -> 53844.531 | F9: =E9*(1+Assumptions!B18) -> 55190.645
A10: Total Operating Expenses | B10: =SUM(B3:B9) -> 590680 | C10: =SUM(C3:C9) -> 605777.6 | D10: =SUM(D3:D9) -> 621262.67 | E10: =SUM(E3:E9) -> 637145.21 | F10: =SUM(F3:F9) -> 653435.45

Sheet NOI
B1: Year 1 | C1: Year 2 | D1: Year 3 | E1: Year 4 | F1: Year 5
A2: Effective Gross Income | B2: =Revenue!B7 -> 1767000 | C2: =Revenue!C7 -> 1819440 | D2: =Revenue!D7 -> 1873441.8 | E2: =Revenue!E7 -> 1929052 | F2: =Revenue!F7 -> 1986318.7
A3: Operating Expenses | B3: =Expenses!B10 -> 590680 | C3: =Expenses!C10 -> 605777.6 | D3: =Expenses!D10 -> 621262.67 | E3: =Expenses!E10 -> 637145.21 | F3: =Expenses!F10 -> 653435.45
A4: Net Operating Income (NOI) | B4: =B2-B3 -> 1176320 | C4: =C2-C3 -> 1213662.4 | D4: =D2-D3 -> 1252179.1 | E4: =E2-E3 -> 1291906.8 | F4: =F2-F3 -> 1332883.2

Sheet Debt Schedule
A2: Purchase Price | B2: =Assumptions!B3 -> 12000000
A3: Loan-to-Value | B3: =Assumptions!B22 -> 0.7
A4: Loan Amount | B4: =B2*B3 -> 8400000
A5: Equity Investment | B5: =B2-B4 -> 3600000
A6: Interest Rate | B6: =Assumptions!B23 -> 0.0625
A7: Loan Term | B7: =Assumptions!B24 -> 30
A8: Annual Payment | B8: =-PMT(B6,B7,B4) -> 626663.83
B10: Year 1 | C10: Year 2 | D10: Year 3 | E10: Year 4 | F10: Year 5
A11: Beginning Balance | B11: =B4 -> 8400000 | C11: =B15 -> 8298336.2 | D11: =C15 -> 8190318.4 | E11: =D15 -> 8075549.4 | F11: =E15 -> 7953607.4
A12: Payment | B12: =B8 -> 626663.83 | C12: =B8 -> 626663.83 | D12: =B8 -> 626663.83 | E12: =B8 -> 626663.83 | F12: =B8 -> 626663.83
A13: Interest | B13: =B11*B6 -> 525000 | C13: =B6*C11 -> 518646.01 | D13: =B6*D11 -> 511894.9 | E13: =B6*E11 -> 504721.84 | F13: =B6*F11 -> 497100.46
A14: Principal | B14: =B12-B13 -> 101663.83 | C14: =C12-C13 -> 108017.82 | D14: =D12-D13 -> 114768.93 | E14: =E12-E13 -> 121941.99 | F14: =F12-F13 -> 129563.37
A15: Ending Balance | B15: =B11-B14 -> 8298336.2 | C15: =C11-C14 -> 8190318.4 | D15: =D11-D14 -> 8075549.4 | E15: =E11-E14 -> 7953607.4 | F15: =F11-F14 -> 7824044.1

Sheet Cash Flow
B1: Year 0 | C1: Year 1 | D1: Year 2 | E1: Year 3 | F1: Year 4 | G1: Year 5
A2: Net Operating Income | C2: =NOI!B4 -> 1176320 | D2: =NOI!C4 -> 1213662.4 | E2: =NOI!D4 -> 1252179.1 | F2: =NOI!E4 -> 1291906.8 | G2: =NOI!F4 -> 1332883.2
A3: Debt Service (Annual Payment) | C3: =-'Debt Schedule'!B8 -> -626663.83 | D3: =-'Debt Schedule'!B8 -> -626663.83 | E3: =-'Debt Schedule'!B8 -> -626663.83 | F3: =-'Debt Schedule'!B8 -> -626663.83 | G3: =-'Debt Schedule'!B8 -> -626663.83
A4: Cash Flow Before Sale | B4: =-'Debt Schedule'!B5 -> -3600000 | C4: =C2+C3 -> 549656.17 | D4: =D2+D3 -> 586998.57 | E4: =E2+E3 -> 625515.3 | F4: =F2+F3 -> 665242.99 | G4: =G2+G3 -> 706219.42
A5: Net Sale Proceeds to Equity | G5: =(G2/Assumptions!B26)-'Debt Schedule'!F15 -> 12681852
A6: Levered Cash Flow to Equity | B6: =B4+B5 -> -3600000 | C6: =C4+C5 -> 549656.17 | D6: =D4+D5 -> 586998.57 | E6: =E4+E5 -> 625515.3 | F6: =F4+F5 -> 665242.99 | G6: =G4+G5 -> 13388071

Sheet Returns
A2: Investment Returns
A3: Initial Equity Investment | B3: ='Debt Schedule'!B5 -> 3600000
A4: Year 1 Cash-on-Cash Return | B4: ='Cash Flow'!C4/Returns!B3 -> 0.15268227
A5: Year 2 Cash-on-Cash Return | B5: ='Cash Flow'!D4/Returns!B3 -> 0.16305516
A6: Year 3 Cash-on-Cash Return | B6: ='Cash Flow'!E4/Returns!B3 -> 0.17375425
A7: Year 4 Cash-on-Cash Return | B7: ='Cash Flow'!F4/Returns!B3 -> 0.18478972
A8: Year 5 Cash-on-Cash Return | B8: ='Cash Flow'!G4/Returns!B3 -> 0.19617206
A9: Equity Multiple (x) | B9: =(SUM('Cash Flow'!C6:G6))/Returns!B3 -> 4.3931901
A10: IRR | B10: =IRR('Cash Flow'!B6:G6) -> 0.39835451
A11: NPV | B11: =NPV(Assumptions!B27,'Cash Flow'!C6:G6)+'Cash Flow'!B6 -> 7509421.7

Sheet Sensitivity Analysis
A2: Exit Cap Rate / Purchase Price | B2: 10000000 | C2: 11000000 | D2: 12000000 | E2: 13000000 | F2: 14000000
A3: 0.055 | B3: =Assumptions!B30 -> 0.56398805 | C3: =Assumptions!C30 -> 0.50819452 | D3: =Assumptions!D30 -> 0.45800774 | E3: =Assumptions!E30 -> 0.41220987 | F3: =Assumptions!F30 -> 0.3698999
A4: 0.06 | B4: =Assumptions!B31 -> 0.53458995 | C4: =Assumptions!C31 -> 0.47805008 | D4: =Assumptions!D31 -> 0.42704507 | E4: =Assumptions!E31 -> 0.38034515 | F4: =Assumptions!F31 -> 0.33703681
A5: 0.065 | B5: =Assumptions!B32 -> 0.50760029 | C5: =Assumptions!C32 -> 0.4502511 | D5: =Assumptions!D32 -> 0.39835451 | E5: =Assumptions!E32 -> 0.35066553 | F5: =Assumptions!F32 -> 0.30625396
A6: 0.07 | B6: =Assumptions!B33 -> 0.48261726 | C6: =Assumptions!C33 -> 0.42439833 | D6: =Assumptions!D33 -> 0.37153717 | E6: =Assumptions!E33 -> 0.32276949 | F6: =Assumptions!F33 -> 0.27714296
A7: 0.075 | B7: =Assumptions!B34 -> 0.45932651 | C7: =Assumptions!C34 -> 0.40017846 | D7: =Assumptions!D34 -> 0.34627845 | E7: =Assumptions!E34 -> 0.2963377 | F7: =Assumptions!F34 -> 0.24937467
A9: Key Takeaways:
A10: Holding the exit cap rate constant, increasing the purchase price consistently reduces IRR.
A11: Holding the purchase price constant, increasing the exit cap rate also reduces IRR.
A12: Purchase price appears to have the larger impact on IRR across the tested ranges.
A13: Increasing the purchase price from $10M to $14M reduces IRR by approximately 20 percentage points on average across the tested exit cap rates.

Sheet Sources
B1: Real Estate Acquisition Model - Sources and Methodology
B2: Category | C2: Source | D2: What it Supports | E2: Reference
B3: Modeling Methodology | C3: OCC | D3: NOI, capitalization, rates, DCF, underwriting and senstivity analysis | E3: OCC Commerical Real Estate Lending
B4: Financing Methodology | C4: FDIC | D4: LTV and CRE lending concepts | E4: FDIC Commerical Real Estate Lending
B5: Modeling Assumptions | C5: Analyst Assumptions | D5: Purchas price, rent, vacancy, expense growth, financing, exit cap, discount rate | E5: Hyporthetical assumptions
B6: Property Data | C6: N/A | D6: No specific property analyzed | E6: Hypothetical investment
B8: Modeling Note: This model represents a hypothetical multifamily real estate acquisition and is intended for educational and portfolio purposes. Property-level assumptions are illustrative and are not based on a specific property or market. The model is designed to demonstrate acquisition underwriting, operating projections, debt financing, cash flow analysis, return calculations, and sensitivity analysis.
