Workbook

Sheet Dashboard

Sheet Assumptions
A2: Property Information
A3: Purchase Price | B3: 12000000
A4: Units | B4: 100
A5: Average Monthly Rent | B5: 1500
A6: Other Monthly Income per Unit | B6: 50
A7: Vacancy Rate | B7: 0.05
A8: Annual Rent Growth | B8: 0.03
A9: Other Income Growth | B9: 0.02
A11: Operating Expenses
A12: Property Taxes | B12: 180000
A13: Insurance | B13: 60000
A14: Repairs and Maintenance | B14: 120000
A15: Property Management (% of Revenue) | B15: 0.04
A16: Utilities | B16: 90000
A17: Other Expenses | B17: 50000
A18: Operating Expense Growth | B18: 0.025
A19: Administrative | B19: 20000
A21: Financing
A22: Loan-to-Value | B22: 0.7
A23: Interest Rate | B23: 0.0625
A24: Loan Term (Years) | B24: 30
A25: Holding Period (Years) | B25: 5

Sheet Revenue
B1: Year 1 | C1: Year 2 | D1: Year 3 | E1: Year 4 | F1: Year 5
A2: Gross Rental Income | B2: =Assumptions!B4*Assumptions!B5*12 -> 1800000 | C2: =B2*(1+Assumptions!B8) -> 1854000 | D2: =C2*(1+Assumptions!B8) -> 1909620 | E2: =D2*(1+Assumptions!B8) -> 1966908.6 | F2: =E2*(1+Assumptions!B8) -> 2025915.9
A3: Other Income | B3: =Assumptions!B4*Assumptions!B6*12 -> 60000 | C3: =B3*(1+Assumptions!B9) -> 61200 | D3: =C3*(1+Assumptions!B9) -> 62424 | E3: =D3*(1+Assumptions!B9) -> 63672.48 | F3: =E3*(1+Assumptions!B9) -> 64945.93
A4: Gross Potential Income | B4: =B2+B3 -> 1860000 | C4: =C2+C3 -> 1915200 | D4: =D2+D3 -> 1972044 | E4: =E2+E3 -> 2030581.1 | F4: =F2+F3 -> 2090861.8
A6: Vacancy Loss | B6: =B4*Assumptions!B7 -> 93000 | C6: =C4*Assumptions!B7 -> 95760 | D6: =D4*Assumptions!B7 -> 98602.2 | E6: =E4*Assumptions!B7 -> 101529.05 | F6: =F4*Assumptions!B7 -> 104543.09
A7: Effective Gross Income | B7: =B4-B6 -> 1767000 | C7: =C4-C6 -> 1819440 | D7: =D4-D6 -> 1873441.8 | E7: =E4-E6 -> 1929052 | F7: =F4-F6 -> 1986318.7

Sheet Expenses
A2: Expense | B2: Year 1 | C2: Year 2 | D2: Year 3 | E2: Year 4 | F2: Year 5
A3: Property Taxes | B3: =Assumptions!B12 -> 180000 | C3: =Expenses!B3*(1+Assumptions!B18) -> 184500 | D3: =C3*(1+Assumptions!B18) -> 189112.5 | E3: =D3*(1+Assumptions!B18) -> 193840.31 | F3: =E3*(1+Assumptions!B18) -> 198686.32
A4: Insurance | B4: =Assumptions!B13 -> 60000 | C4: =B4*(1+Assumptions!B18) -> 61500 | D4: =C4*(1+Assumptions!B18) -> 63037.5 | E4: =D4*(1+Assumptions!B18) -> 64613.437 | F4: =E4*(1+Assumptions!B18) -> 66228.773
A5: Repairs & Maintenance | B5: =Assumptions!B14 -> 120000 | C5: =B5*(1+Assumptions!B18) -> 123000 | D5: =C5*(1+Assumptions!B18) -> 126075 | E5: =D5*(1+Assumptions!B18) -> 129226.87 | F5: =E5*(1+Assumptions!B18) -> 132457.55
A6: Property Management | B6: =Revenue!B7*Assumptions!B15 -> 70680 | C6: =Revenue!C7*Assumptions!B15 -> 72777.6 | D6: =Revenue!D7*Assumptions!B15 -> 74937.672 | E6: =Revenue!E7*Assumptions!B15 -> 77162.081 | F6: =Revenue!F7*Assumptions!B15 -> 79452.748
A7: Utilities | B7: =Assumptions!B16 -> 90000 | C7: =B7*(1+Assumptions!B18) -> 92250 | D7: =C7*(1+Assumptions!B18) -> 94556.25 | E7: =D7*(1+Assumptions!B18) -> 96920.156 | F7: =E7*(1+Assumptions!B18) -> 99343.16
A8: Administrative | B8: =Assumptions!B19 -> 20000 | C8: =B8*(1+Assumptions!B18) -> 20500 | D8: =C8*(1+Assumptions!B18) -> 21012.5 | E8: =D8*(1+Assumptions!B18) -> 21537.812 | F8: =E8*(1+Assumptions!B18) -> 22076.258
A9: Other Expenses | B9: =Assumptions!B17 -> 50000 | C9: =B9*(1+Assumptions!B18) -> 51250 | D9: =C9*(1+Assumptions!B18) -> 52531.25 | E9: =D9*(1+Assumptions!B18) -> 53844.531 | F9: =E9*(1+Assumptions!B18) -> 55190.645
A10: Total Operating Expenses | B10: =SUM(B3:B9) -> 590680 | C10: =SUM(C3:C9) -> 605777.6 | D10: =SUM(D3:D9) -> 621262.67 | E10: =SUM(E3:E9) -> 637145.21 | F10: =SUM(F3:F9) -> 653435.45

Sheet NOI
B1: Year 1 | C1: Year 2 | D1: Year 3 | E1: Year 4 | F1: Year 5
A2: Effective Gross Income | B2: =Revenue!B7 -> 1767000 | C2: =Revenue!C2 -> 1854000 | D2: =Revenue!D2 -> 1909620 | E2: =Revenue!E2 -> 1966908.6 | F2: =Revenue!F2 -> 2025915.9
A3: Operating Expenses | B3: =Expenses!B10 -> 590680 | C3: =Expenses!C10 -> 605777.6 | D3: =Expenses!D10 -> 621262.67 | E3: =Expenses!E10 -> 637145.21 | F3: =Expenses!F10 -> 653435.45
A4: Net Operating Income (NOI) | B4: =B2-B3 -> 1176320 | C4: =C2-C3 -> 1248222.4 | D4: =D2-D3 -> 1288357.3 | E4: =E2-E3 -> 1329763.4 | F4: =F2-F3 -> 1372480.4

Sheet Debt
A2: Purchase Price | B2: =Assumptions!B3 -> 12000000
A3: Loan-to-Value | B3: =Assumptions!B22 -> 0.7
A4: Loan Amount | B4: =B2*B3 -> 8400000
A5: Equity Investment | B5: =B2-B4 -> 3600000
A6: Interest Rate | B6: =Assumptions!B23 -> 0.0625
A7: Loan Term | B7: =Assumptions!B24 -> 30
A8: Annual Payment | B8: =PMT(B6,B7,B4) -> -626663.83
B10: Year 1 | C10: Year 2 | D10: Year 3 | E10: Year 4 | F10: Year 5
A11: Beginning Balance | B11: =B4 -> 8400000 | C11: =B15 -> 8298336.2 | D11: =C15 -> 8190318.4 | E11: =D15 -> 8075549.4 | F11: =E15 -> 7953607.4
A12: Payment | B12: =B8 -> -626663.83 | C12: =B8 -> -626663.83 | D12: =B8 -> -626663.83 | E12: =B8 -> -626663.83 | F12: =B8 -> -626663.83
A13: Interest | B13: =B11*B6 -> 525000 | C13: =B6*C11 -> 518646.01 | D13: =B6*D11 -> 511894.9 | E13: =B6*E11 -> 504721.84 | F13: =B6*F11 -> 497100.46
A14: Principal | B14: =(-1*B12)-B13 -> 101663.83 | C14: =(-1*C12)-C13 -> 108017.82 | D14: =(-1*D12)-D13 -> 114768.93 | E14: =(-1*E12)-E13 -> 121941.99 | F14: =(-1*F12)-F13 -> 129563.37
A15: Ending Balance | B15: =B11-B14 -> 8298336.2 | C15: =C11-C14 -> 8190318.4 | D15: =D11-D14 -> 8075549.4 | E15: =E11-E14 -> 7953607.4 | F15: =F11-F14 -> 7824044.1

Sheet Cash Flow

Sheet Returns

Sheet Sensitivity Analysis

Sheet Sources

Sheet Notes
B2: Why do we subtract vacancy?
B3: Why is revenue projected instead of kept constant?
B4: Which assumption do I think has the biggest impact on revenue?
